qt_log/__init__.py
qt_log/qt_ui_logger.py
qt_log/stream_log.py
qt_log/version.py
qt_log-1.1.3.dist-info/METADATA
qt_log-1.1.3.dist-info/WHEEL
qt_log-1.1.3.dist-info/RECORD
