Metadata-Version: 2.1
Name: qt-log
Version: 1.1.3
Summary: Qt Custom UI Log for Maya/Houdini
Home-page: https://github.com/MaxRocamora/QtLog
License: MIT
Author: Maximiliano Rocamora
Author-email: maxirocamora@gmail.com
Requires-Python: >=3.7,<3.15
Classifier: Intended Audience :: Developers
Classifier: License :: OSI Approved :: MIT License
Classifier: Operating System :: OS Independent
Classifier: Programming Language :: Python :: 3
Classifier: Programming Language :: Python :: 3.7
Classifier: Programming Language :: Python :: 3.8
Classifier: Programming Language :: Python :: 3.9
Classifier: Programming Language :: Python :: 3.10
Classifier: Programming Language :: Python :: 3.11
Classifier: Programming Language :: Python :: 3.12
Classifier: Programming Language :: Python :: 3.13
Classifier: Programming Language :: Python :: 3.14
